snowball_stemmer.cpython-39-x86_64-linux-gnu.so
snowball_stemmer_wheels-0.1.0.dist-info/top_level.txt
snowball_stemmer_wheels-0.1.0.dist-info/AUTHORS
snowball_stemmer_wheels-0.1.0.dist-info/METADATA
snowball_stemmer_wheels-0.1.0.dist-info/WHEEL
snowball_stemmer_wheels-0.1.0.dist-info/RECORD
snowball_stemmer_wheels-0.1.0.dist-info/LICENSE
