Metadata-Version: 2.1
Name: snowball_stemmer_wheels
Version: 0.1.0
Summary: A fork of PyStemmer with pure wheels 
Home-page: https://github.com/xhluca/snowball_stemmer
Author: Richard Boulton
Maintainer: Richard Boulton, Xing Han Lu
License: MIT, BSD
Keywords: python,information retrieval,language processing,morphological analysis,stemming algorithms,stemmers
Platform: any
Classifier: Development Status :: 5 - Production/Stable
Classifier: Intended Audience :: Developers
Classifier: License :: OSI Approved :: MIT License
Classifier: License :: OSI Approved :: BSD License
Classifier: Natural Language :: Danish
Classifier: Natural Language :: Dutch
Classifier: Natural Language :: English
Classifier: Natural Language :: Finnish
Classifier: Natural Language :: French
Classifier: Natural Language :: German
Classifier: Natural Language :: Italian
Classifier: Natural Language :: Norwegian
Classifier: Natural Language :: Portuguese
Classifier: Natural Language :: Russian
Classifier: Natural Language :: Spanish
Classifier: Natural Language :: Swedish
Classifier: Operating System :: OS Independent
Classifier: Programming Language :: C
Classifier: Programming Language :: Other
Classifier: Programming Language :: Python
Classifier: Programming Language :: Python :: 2
Classifier: Programming Language :: Python :: 2.6
Classifier: Programming Language :: Python :: 2.7
Classifier: Programming Language :: Python :: 3
Classifier: Programming Language :: Python :: 3.3
Classifier: Programming Language :: Python :: 3.4
Classifier: Programming Language :: Python :: 3.5
Classifier: Programming Language :: Python :: 3.6
Classifier: Programming Language :: Python :: 3.7
Classifier: Programming Language :: Python :: 3.8
Classifier: Programming Language :: Python :: 3.9
Classifier: Programming Language :: Python :: 3.10
Classifier: Programming Language :: Python :: 3.11
Classifier: Programming Language :: Python :: 3.12
Classifier: Topic :: Database
Classifier: Topic :: Internet :: WWW/HTTP :: Indexing/Search
Classifier: Topic :: Text Processing :: Indexing
Classifier: Topic :: Text Processing :: Linguistic
License-File: LICENSE
License-File: AUTHORS
